README.md
setup.cfg
setup.py
JenkinsLibrary/__init__.py
JenkinsLibrary/jenkins_face.py
JenkinsLibrary/version.py
robotframework_jenkinslibrary.egg-info/PKG-INFO
robotframework_jenkinslibrary.egg-info/SOURCES.txt
robotframework_jenkinslibrary.egg-info/dependency_links.txt
robotframework_jenkinslibrary.egg-info/requires.txt
robotframework_jenkinslibrary.egg-info/top_level.txt
tests/__init__.py
tests/test_build_jenkins_with_parameters.py
tests/test_build_jenkins_with_parameters_and_wait_until_job_done.py
tests/test_get_jenkins_job.py
tests/test_get_jenkins_job_build.py
tests/test_jenkins_session.py