Metadata-Version: 2.1
Name: robotframework-jenkinslibrary
Version: 0.8.5
Summary: Jenkins wrapper library for robotframework
Home-page: https://github.com/robotframework-thailand/robotframework-jenkinslibrary.git
Author: Panchorn Lertvipada, Nitipat Phiphatprathuang, Kanokwan Suttidee
Author-email: nonpcn@gmail.com, banknitipat@gmail.com, kanokwan.sut94@gmail.com
License: MIT
Platform: UNKNOWN
Classifier: Development Status :: 3 - Alpha
Classifier: Intended Audience :: Developers
Classifier: Topic :: Software Development :: Testing
Classifier: License :: OSI Approved :: MIT License
Classifier: Programming Language :: Python :: 3
Classifier: Operating System :: OS Independent
Classifier: Programming Language :: Python
Classifier: Programming Language :: Python :: 3
Classifier: Programming Language :: Python :: 3.5
Classifier: Programming Language :: Python :: 3.6
Classifier: Programming Language :: Python :: 3.7
